df_cli/__init__.py
df_cli/cli.py
df_cli/df_request.py
dfinder-0.1.0.dist-info/METADATA
dfinder-0.1.0.dist-info/RECORD
dfinder-0.1.0.dist-info/WHEEL
dfinder-0.1.0.dist-info/entry_points.txt
dfinder-0.1.0.dist-info/top_level.txt
