Metadata-Version: 2.1
Name: dfinder
Version: 0.1.0
Summary: A command line interface for DockerFinder.
Home-page: https://github.com/lucarin91/dockerfinder-cli
Author: lucarin
Author-email: to@lucar.in
License: MIT license
Keywords: dfinder
Platform: UNKNOWN
Classifier: Development Status :: 2 - Pre-Alpha
Classifier: Intended Audience :: Developers
Classifier: License :: OSI Approved :: MIT License
Classifier: Natural Language :: English
Classifier: Programming Language :: Python :: 2
Classifier: Programming Language :: Python :: 2.7
Classifier: Programming Language :: Python :: 3
Classifier: Programming Language :: Python :: 3.4
Classifier: Programming Language :: Python :: 3.5
Classifier: Programming Language :: Python :: 3.6
Requires-Dist: Click (>=6.0)
Requires-Dist: tabulate
